push_message/__init__.py
push_message/exceptions.py
push_message/qywx.py
push_message-0.0.2.dist-info/LICENSE
push_message-0.0.2.dist-info/METADATA
push_message-0.0.2.dist-info/WHEEL
push_message-0.0.2.dist-info/top_level.txt
push_message-0.0.2.dist-info/RECORD
