Metadata-Version: 2.1
Name: push-message
Version: 0.0.2
Summary: Push messages via multiple ways
Author-email: Ma Xiaowei <maxiaowei0216@gmail.com>
Project-URL: Homepage, https://github.com/maxiaowei0216/push-message-pypi
Project-URL: Bug Tracker, https://github.com/maxiaowei0216/push-message-pypi/issues
Classifier: Programming Language :: Python :: 3
Classifier: License :: OSI Approved :: MIT License
Classifier: Operating System :: OS Independent
Requires-Python: >=3.7
License-File: LICENSE
Requires-Dist: requests
